[
  {
    "classIndex": 0,
    "x": 1454.92128,
    "y": 415.24325999999996,
    "w": 86.5056,
    "h": 78.04404
  },
  {
    "classIndex": 0,
    "x": 832.03872,
    "y": 510.5872800000001,
    "w": 94.07039999999999,
    "h": 82.96992
  },
  {
    "classIndex": 0,
    "x": 323.98463999999996,
    "y": 536.05584,
    "w": 98.64192,
    "h": 89.86248
  },
  {
    "classIndex": 0,
    "x": 1534.83168,
    "y": 473.76629999999994,
    "w": 111.82272,
    "h": 67.38012
  },
  {
    "classIndex": 0,
    "x": 1512.1968,
    "y": 588.74742,
    "w": 95.49888,
    "h": 73.91412
  }
]