[
  {
    "classIndex": 0,
    "x": 229.30003288905033,
    "y": 539.6563148110075,
    "w": 112.00000712076866,
    "h": 115.00001299822918
  },
  {
    "classIndex": 0,
    "x": 1403.3001075299649,
    "y": 567.6563179757937,
    "w": 147.00000934600894,
    "h": 93.00001051161144
  },
  {
    "classIndex": 0,
    "x": 1442.3001100095182,
    "y": 407.65629989130093,
    "w": 103.00000654856399,
    "h": 88.00000994647104
  },
  {
    "classIndex": 1,
    "x": 1129.5,
    "y": 504.546875,
    "w": 22,
    "h": 25
  },
  {
    "classIndex": 1,
    "x": 1126.5,
    "y": 555.546875,
    "w": 20,
    "h": 19
  },
  {
    "classIndex": 1,
    "x": 1102.5,
    "y": 550.546875,
    "w": 21,
    "h": 23
  },
  {
    "classIndex": 1,
    "x": 1111.5,
    "y": 514.546875,
    "w": 20,
    "h": 20
  },
  {
    "classIndex": 1,
    "x": 1147.5,
    "y": 515.546875,
    "w": 21,
    "h": 24
  },
  {
    "classIndex": 1,
    "x": 1157.5,
    "y": 463.546875,
    "w": 20,
    "h": 20
  },
  {
    "classIndex": 1,
    "x": 1046.5,
    "y": 493.546875,
    "w": 25,
    "h": 21
  },
  {
    "classIndex": 1,
    "x": 999.5,
    "y": 549.546875,
    "w": 22,
    "h": 18
  },
  {
    "classIndex": 1,
    "x": 1007.5,
    "y": 393.546875,
    "w": 21,
    "h": 20
  },
  {
    "classIndex": 1,
    "x": 773.5,
    "y": 526.546875,
    "w": 25,
    "h": 20
  },
  {
    "classIndex": 1,
    "x": 662.5,
    "y": 519.546875,
    "w": 25,
    "h": 19
  },
  {
    "classIndex": 1,
    "x": 1460.5,
    "y": 692.546875,
    "w": 28,
    "h": 27
  },
  {
    "classIndex": 1,
    "x": 1555.5,
    "y": 705.546875,
    "w": 28,
    "h": 31
  },
  {
    "classIndex": 1,
    "x": 1682.5,
    "y": 570.546875,
    "w": 27,
    "h": 24
  },
  {
    "classIndex": 1,
    "x": 1568.5,
    "y": 379.546875,
    "w": 22,
    "h": 21
  },
  {
    "classIndex": 1,
    "x": 1177.5,
    "y": 488.546875,
    "w": 20,
    "h": 23
  },
  {
    "classIndex": 1,
    "x": 1881.3001379203884,
    "y": 754.2563375409544,
    "w": 35.00000222524022,
    "h": 41.00000463415131
  }
]